{"defaultParserType":"jacred","remoteConfigUrl":"","remoteConfigEnabled":false,"defaultTorrServerUrl":"http://pape85e.tsarea.tv:8880","parsers":[{"name":"Default JacRed/Torznab Parser","type":"jacred","url":"http://pape85e.tsarea.tv:8880","apiKey":"","apiKeyRequired":false,"priority":1,"enabled":true,"notes":"default user-visible parser candidate; tested before use"},{"name":"User JacRed Parser","type":"jacred","url":"USER_CONFIGURED_PARSER_URL","apiKey":"","apiKeyRequired":false,"priority":50,"enabled":false,"notes":"configure your own JacRed-compatible parser in Settings"},{"name":"User Torznab Parser","type":"torznab","url":"USER_CONFIGURED_TORZNAB_URL","apiKey":"","apiKeyRequired":false,"priority":60,"enabled":false,"notes":"configure your own Torznab-compatible parser in Settings"}]}
